yt_dlp_expand/__init__.py
yt_dlp_expand/main_script.py
yt_dlp_expand-0.4.10.dist-info/METADATA
yt_dlp_expand-0.4.10.dist-info/WHEEL
yt_dlp_expand-0.4.10.dist-info/entry_points.txt
yt_dlp_expand-0.4.10.dist-info/top_level.txt
yt_dlp_expand-0.4.10.dist-info/RECORD
