Metadata-Version: 2.4
Name: yt_dlp_expand
Version: 0.4.10
Summary: 説明
Author-email: souno1218 <supinosaurusuz@gmail.com>
License: MIT License
Project-URL: Homepage, https://qiita.com/soun1218/items/3f07fbaa7029208dd789
Requires-Python: >=3.10
Requires-Dist: yt-dlp[default]
Requires-Dist: mutagen
Requires-Dist: ffmpeg-python>=0.2.0
Requires-Dist: twine>=6.1.0
Requires-Dist: build>=1.2.2.post1
